setup.py
algpygame/__init__.py
algpygame.egg-info/PKG-INFO
algpygame.egg-info/SOURCES.txt
algpygame.egg-info/dependency_links.txt
algpygame.egg-info/top_level.txt