Metadata-Version: 2.1
Name: algpygame
Version: 0.0.1
Summary: 奥利给硬件科技工作室pygame函数库
Home-page: https://alggfzslt.freeflarum.com/
Author: algfwq
Author-email: 3104374883@qq.com
License: MIT License
Platform: UNKNOWN
Requires: pygame
